jinsung/__init__.py
jinsung/ha.py
jinsung_ha/__init__.py
jinsung_ha/jinsung_ha.py
jinsung-0.2.0.dist-info/LICENSE
jinsung-0.2.0.dist-info/METADATA
jinsung-0.2.0.dist-info/WHEEL
jinsung-0.2.0.dist-info/top_level.txt
jinsung-0.2.0.dist-info/RECORD
