Metadata-Version: 2.1
Name: jinsung
Version: 0.2.0
Summary: Who is Jinsung Ha?
Home-page: https://github.com/jha929/jha929
Author: Jinsung Ha
Author-email: jsung5381@naver.com
License: MIT
Platform: UNKNOWN
Classifier: Programming Language :: Python :: 3
Classifier: License :: OSI Approved :: MIT License
Classifier: Operating System :: OS Independent
